.DS_Store
fsight/__init__.py
fsight/__main__.py
fsight/pio.py
fsight_cli-0.74.dist-info/DESCRIPTION.rst
fsight_cli-0.74.dist-info/METADATA
fsight_cli-0.74.dist-info/RECORD
fsight_cli-0.74.dist-info/WHEEL
fsight_cli-0.74.dist-info/entry_points.txt
fsight_cli-0.74.dist-info/metadata.json
fsight_cli-0.74.dist-info/top_level.txt
pio/__init__.py
pio/__main__.py
pio/pio.py
